data_auditor/__init__.py
data_auditor/fairness.py
data_auditor/preprocessing.py
data_auditor/profiler.py
data_auditor/utils.py
data_auditor/encoders/custom_transformer.py
data_auditor/encoders/onehot.py
data_auditor/encoders/ordinal.py
data_auditor-0.1.4.dist-info/METADATA
data_auditor-0.1.4.dist-info/WHEEL
data_auditor-0.1.4.dist-info/top_level.txt
data_auditor-0.1.4.dist-info/RECORD
