Metadata-Version: 2.4
Name: data-auditor
Version: 0.1.4
Summary: A modular profiling and preprocessing library for tabular ML datasets
Author-email: miriamspsantos <miriam.santos@fc.up.pt>
License: MIT
Project-URL: Homepage, https://github.com/miriamspsantos/data-auditor
Requires-Python: <=3.13
Requires-Dist: pandas
Requires-Dist: scikit-learn
Requires-Dist: matplotlib
Requires-Dist: seaborn
